fichs/vocEstomas.names
fichs/yolov3Estomas.cfg
labelStomaMarion/__init__.py
labelStomaMarion/clodsa.py
labelStomaMarion/labelStomaMarion.py
labelstomamarion-2.4.dist-info/licenses/LICENSE
libs/__init__.py
libs/canvas.py
libs/colorDialog.py
libs/constants.py
libs/excelDialog.py
libs/excelMarion.py
libs/hashableQListWidgetItem.py
libs/labelDialog.py
libs/labelFile.py
libs/linea.py
libs/pascal_voc_io.py
libs/resources.py
libs/settings.py
libs/shape.py
libs/stomaExcel.py
libs/stringBundle.py
libs/toolBar.py
libs/ustr.py
libs/utils.py
libs/version.py
libs/yolo_io.py
libs/zoomWidget.py
notebooks/notebookYolo.py
predict/detect.py
predict/detectStoma.py
predict/generateExcelStoma.py
predict/selectPesos.py
labelstomamarion-2.4.dist-info/METADATA
labelstomamarion-2.4.dist-info/WHEEL
labelstomamarion-2.4.dist-info/entry_points.txt
labelstomamarion-2.4.dist-info/top_level.txt
labelstomamarion-2.4.dist-info/RECORD
