Metadata-Version: 2.4
Name: labelStomaMarion
Version: 2.4
Summary: labelStoma is a graphical tool for using and creating detection models
Author: Angela Casado
Author-email: angela.casado@unirioja.es
License: MIT license
Keywords: labelStomaMarion detection deeplearning
Classifier: Development Status :: 5 - Production/Stable
Classifier: Intended Audience :: Developers
Classifier: License :: OSI Approved :: MIT License
Classifier: Natural Language :: English
Classifier: Programming Language :: Python :: 3
Classifier: Programming Language :: Python :: 3.3
Classifier: Programming Language :: Python :: 3.4
Classifier: Programming Language :: Python :: 3.5
Classifier: Programming Language :: Python :: 3.6
Classifier: Programming Language :: Python :: 3.7
Requires-Python: >=3.12
License-File: LICENSE
Requires-Dist: pyqt5
Requires-Dist: lxml
Requires-Dist: imutils==0.5.4
Requires-Dist: tqdm==4.67.1
Requires-Dist: XlsxWriter==3.2.3
Requires-Dist: six==1.17.0
Requires-Dist: numpy==2.2.4
Requires-Dist: progressbar2==3.47.0
Requires-Dist: scikit_learn==1.6.1
Requires-Dist: pandas
Requires-Dist: xlwt==1.3.0
Requires-Dist: sip==1.17.0
Dynamic: author
Dynamic: author-email
Dynamic: classifier
Dynamic: description
Dynamic: keywords
Dynamic: license
Dynamic: license-file
Dynamic: requires-dist
Dynamic: requires-python
Dynamic: summary
